gxformat2/__init__.py
gxformat2/_labels.py
gxformat2/_scripts.py
gxformat2/_yaml.py
gxformat2/abstract.py
gxformat2/converter.py
gxformat2/cytoscape.html
gxformat2/cytoscape.py
gxformat2/export.py
gxformat2/interface.py
gxformat2/lint.py
gxformat2/linting.py
gxformat2/main.py
gxformat2/markdown_parse.py
gxformat2/model.py
gxformat2/normalize.py
gxformat2/yaml.py
gxformat2/schema/__init__.py
gxformat2/schema/v19_09.py
gxformat2-0.21.0.dist-info/LICENSE
gxformat2-0.21.0.dist-info/METADATA
gxformat2-0.21.0.dist-info/WHEEL
gxformat2-0.21.0.dist-info/entry_points.txt
gxformat2-0.21.0.dist-info/top_level.txt
gxformat2-0.21.0.dist-info/RECORD
